django_yandex_captcha/__init__.py
django_yandex_captcha/apps.py
django_yandex_captcha/client.py
django_yandex_captcha/constants.py
django_yandex_captcha/fields.py
django_yandex_captcha/widgets.py
django_yandex_captcha/templates/django_yandex_captcha/widget.html
django_yandex_captcha/templates/django_yandex_captcha/includes/js.html
django_yandex_captcha-0.0.5.dist-info/licenses/LICENSE
django_yandex_captcha-0.0.5.dist-info/METADATA
django_yandex_captcha-0.0.5.dist-info/WHEEL
django_yandex_captcha-0.0.5.dist-info/top_level.txt
django_yandex_captcha-0.0.5.dist-info/RECORD
